ubuntu-postinstall/__init__.py
ubuntu-postinstall/main.py
ubuntu-postinstall/mainwindow.py
ubuntu-postinstall/models/__init__.py
ubuntu-postinstall/models/action.py
ubuntu-postinstall/models/action_status.py
ubuntu-postinstall/models/command.py
ubuntu-postinstall/models/command_function.py
ubuntu-postinstall/models/command_line.py
ubuntu-postinstall/models/system_action.py
ubuntu-postinstall/tests/__init__.py
ubuntu-postinstall/tests/test_action.py
ubuntu-postinstall/tests/test_action_status.py
ubuntu-postinstall/tests/test_command_function.py
ubuntu-postinstall/tests/test_command_line.py
ubuntu-postinstall/tests/test_system_action.py
ubuntu-postinstall/utils/__init__.py
ubuntu-postinstall/utils/gnome_utils.py
ubuntu-postinstall/views/__init__.py
ubuntu-postinstall/views/ui_main_window.py
ubuntu_postinstall/__init__.py
ubuntu_postinstall/main.py
ubuntu_postinstall/mainwindow.py
ubuntu_postinstall/models/__init__.py
ubuntu_postinstall/models/action.py
ubuntu_postinstall/models/action_status.py
ubuntu_postinstall/models/command.py
ubuntu_postinstall/models/command_function.py
ubuntu_postinstall/models/command_line.py
ubuntu_postinstall/models/system_action.py
ubuntu_postinstall/tests/__init__.py
ubuntu_postinstall/tests/test_action.py
ubuntu_postinstall/tests/test_action_status.py
ubuntu_postinstall/tests/test_command_function.py
ubuntu_postinstall/tests/test_command_line.py
ubuntu_postinstall/tests/test_system_action.py
ubuntu_postinstall/utils/__init__.py
ubuntu_postinstall/utils/gnome_utils.py
ubuntu_postinstall/views/__init__.py
ubuntu_postinstall/views/ui_main_window.py
ubuntu_postinstall-0.0.1.dist-info/LICENSE
ubuntu_postinstall-0.0.1.dist-info/METADATA
ubuntu_postinstall-0.0.1.dist-info/WHEEL
ubuntu_postinstall-0.0.1.dist-info/entry_points.txt
ubuntu_postinstall-0.0.1.dist-info/top_level.txt
ubuntu_postinstall-0.0.1.dist-info/RECORD
