Metadata-Version: 2.1
Name: ubuntu-postinstall
Version: 0.0.1
Summary: Automatic setup tool for fresh Ubuntu installs
Author: hagyma (Varga Dániel)
Author-email: vargad0803@gmail.com
Keywords: python,ubuntu,postinstall,extensions,dconf,gsettings
License-File: LICENSE
Requires-Dist: pyside6
